googly/__init__.py
googly/_version.py
googly/api.py
googly/scope.py
googly/util.py
googly/apps/calendar.py
googly/apps/drive.py
googly/apps/gmail.py
googly/apps/people.py
googly/apps/photos.py
googly/apps/sheets.py
googly/apps/youtube.py
googly-0.2.0.dist-info/METADATA
googly-0.2.0.dist-info/WHEEL
googly-0.2.0.dist-info/licenses/LICENSE
googly-0.2.0.dist-info/RECORD
