Metadata-Version: 2.3
Name: googly
Version: 0.2.0
Summary: A simple unofficial Python API for many Google APIs
Project-URL: Homepage, https://github.com/DLu/googly
Project-URL: Bug Tracker, https://github.com/DLu/googly/issues
Author-email: "David V. Lu!!" <davidvlu@gmail.com>
Maintainer-email: "David V. Lu!!" <davidvlu@gmail.com>
License-File: LICENSE
Classifier: Development Status :: 3 - Alpha
Classifier: License :: OSI Approved :: BSD License
Classifier: Programming Language :: Python :: 3
Classifier: Topic :: Communications :: Email
Classifier: Topic :: Internet
Classifier: Topic :: Office/Business :: Financial :: Spreadsheet
Classifier: Topic :: Office/Business :: Scheduling
Requires-Python: >=3.8
Requires-Dist: google-api-python-client
Requires-Dist: google-auth-httplib2
Requires-Dist: google-auth-oauthlib
Provides-Extra: docs
Requires-Dist: myst-parser>=0.13; extra == 'docs'
Requires-Dist: sphinx>=4.0; extra == 'docs'
Provides-Extra: test
Requires-Dist: pytest-cov>=2; extra == 'test'
Requires-Dist: pytest>=4; extra == 'test'
